tjwmd/__init__.py
tjwmd/digits_labels.py
tjwmd/tjwmd.py
tjwmd/utils.py
tjwmd-2.0.0.dist-info/METADATA
tjwmd-2.0.0.dist-info/WHEEL
tjwmd-2.0.0.dist-info/RECORD
