Metadata-Version: 2.1
Name: tjwmd
Version: 2.0.0
Summary: tjwmd
Home-page: https://github.com/duynguyen02/tjwmd
Author: Duy Nguyen
Author-email: duynguyen02.dev@gmail.com
Requires-Python: >=3.9,<4.0
Classifier: Programming Language :: Python :: 3
Classifier: Programming Language :: Python :: 3.9
Classifier: Programming Language :: Python :: 3.10
Classifier: Programming Language :: Python :: 3.11
Classifier: Programming Language :: Python :: 3.12
Requires-Dist: opencv-python (>=4.10.0.84,<5.0.0.0)
Requires-Dist: ultralytics (>=8.2.83,<9.0.0)
Project-URL: Repository, https://github.com/duynguyen02/tjwmd
